pass_prot_pdf/app.py
pass_prot_pdf/settings.py
pass_prot_pdf/start.py
pass_prot_pdf/utils.py
pass_prot_pdf-0.1.5.dist-info/entry_points.txt
pass_prot_pdf-0.1.5.dist-info/METADATA
pass_prot_pdf-0.1.5.dist-info/WHEEL
pass_prot_pdf-0.1.5.dist-info/RECORD
